vivid/root/__init__.py
vivid_root-0.0.1.dist-info/LICENSE
vivid_root-0.0.1.dist-info/METADATA
vivid_root-0.0.1.dist-info/WHEEL
vivid_root-0.0.1.dist-info/top_level.txt
vivid_root-0.0.1.dist-info/zip-safe
vivid_root-0.0.1.dist-info/RECORD
